odoo10_addon_donation_sale-10.0.1.0.0.99.dev13-py3.8-nspkg.pth
odoo/addons/donation_sale/README.rst
odoo/addons/donation_sale/__init__.py
odoo/addons/donation_sale/__manifest__.py
odoo/addons/donation_sale/data/cron.xml
odoo/addons/donation_sale/i18n/de.po
odoo/addons/donation_sale/i18n/donation_sale.pot
odoo/addons/donation_sale/i18n/fr.po
odoo/addons/donation_sale/models/__init__.py
odoo/addons/donation_sale/models/donation_sale.py
odoo/addons/donation_sale/static/description/icon.png
odoo/addons/donation_sale/views/account_invoice.xml
odoo/addons/donation_sale/views/donation_tax.xml
odoo/addons/donation_sale/views/sale_order.xml
odoo10_addon_donation_sale-10.0.1.0.0.99.dev13.dist-info/METADATA
odoo10_addon_donation_sale-10.0.1.0.0.99.dev13.dist-info/WHEEL
odoo10_addon_donation_sale-10.0.1.0.0.99.dev13.dist-info/namespace_packages.txt
odoo10_addon_donation_sale-10.0.1.0.0.99.dev13.dist-info/top_level.txt
odoo10_addon_donation_sale-10.0.1.0.0.99.dev13.dist-info/RECORD
